natbus/__init__.py
natbus/client.py
natbus/config.py
natbus/message.py
natbus-0.2.2.dist-info/licenses/LICENSE
natbus-0.2.2.dist-info/METADATA
natbus-0.2.2.dist-info/WHEEL
natbus-0.2.2.dist-info/top_level.txt
natbus-0.2.2.dist-info/RECORD
