Metadata-Version: 2.4
Name: natbus
Version: 0.2.2
Summary: Minimal NATS JetStream client for internal services
Author-email: Servicepod <admin@servicepod.net>
License: MIT License
Project-URL: Homepage, https://servicepod.net
Project-URL: Source, https://servicepod.net
Project-URL: Issues, https://servicepod.net
Keywords: nats,jetstream,messaging,asyncio
Classifier: Programming Language :: Python :: 3
Classifier: Programming Language :: Python :: 3 :: Only
Classifier: Programming Language :: Python :: 3.11
Classifier: License :: OSI Approved :: MIT License
Classifier: Operating System :: OS Independent
Classifier: Framework :: AsyncIO
Requires-Python: >=3.11
License-File: LICENSE
Requires-Dist: nats-py>=2.11.0
Dynamic: license-file
